{
    "build": {
        "dockerfile": "${localWorkspaceFolder}/Dockerfile",
        "target": "base"
    },
    "workspaceMount": "source=${localWorkspaceFolder},target=/app,type=bind",
    "workspaceFolder": "/app",
    "runArgs": [
        "--network=host",
        "--env=CASSANDRA_HOST=127.0.0.1",
        "--env=CASSANDRA_PORT=9043"
    ],
    "containerEnv": {
        "CASSANDRA_HOST": "cassandra"
    },
    "customizations": {
        "vscode": {
            "extensions": [
                "EditorConfig.EditorConfig",
                "ms-vscode.cmake-tools",
                "ms-azuretools.vscode-docker",
                "redhat.vscode-yaml",
                "llvm-vs-code-extensions.vscode-clangd",
                "twxs.cmake"
            ]
        }
    },
    "features": {
        "ghcr.io/devcontainers/features/git:1": {
            "version": "latest"
        },
        "ghcr.io/devcontainers/features/common-utils:1": {
            "version": "latest"
        }
    }
}
